{
"elderly":["https://rsvp.org.sg/activities/","https://ntuchealth.sg/volunteer","https://www.giving.sg/volunteer-event?event_activity_id=77614488","https://www.giving.sg/volunteer-event?event_activity_id=76857194","https://www.giving.sg/volunteer-event?event_activity_id=76805964"],
    
"animals":["https://docs.google.com/forms/d/e/1FAIpQLSfAqWpJjJMVTIG1wx81bJeMu1bakr-YymaLyg8BFAoWAqS1rA/viewform?c=0&w=1","https://www.causesforanimals.com/volunteering.html"],

"community service":["https://www.volunteer.gov.sg/volunteer/home","https://www.giving.sg","https://www.giving.sg/volunteer-event?event_activity_id=77357266"],

"children":["https://www.givlly.com/tsa/volunteer_register","https://www.wishingwell.org.sg/volunteer/","https://www.giving.sg/volunteer-event?event_activity_id=77632254"],

"events":["https://www.giving.sg/volunteer-event?event_activity_id=76233029","https://www.giving.sg/volunteer-event?event_activity_id=77527171"],

"others":["https://www.giving.sg/volunteer-event?event_activity_id=77508316","https://www.giving.sg/volunteer-event?event_activity_id=76021725","https://www.giving.sg/volunteer-event?event_activity_id=76904386","https://www.giving.sg/volunteer-event?event_activity_id=76484040"]

}
